faq/__init__.py
faq/db_elastic/__init__.py
faq/db_elastic/document.py
faq/db_elastic/engine.py
faq/db_elastic/tests.py
faq/faq_admin/__init__.py
faq/faq_admin/admin.py
faq/faq_admin/apps.py
faq/faq_admin/models.py
faq/faq_admin/orm_utils.py
faq/faq_admin/validators.py
faq/faq_admin/migrations/0001_initial.py
faq/faq_admin/migrations/__init__.py
faq/faq_tbot/__init__.py
faq/faq_tbot/dispatcher.py
faq/faq_tbot/keyboards.py
faq/faq_tbot/translations.py
django_bot_faq-0.2.1.dist-info/LICENSE
django_bot_faq-0.2.1.dist-info/METADATA
django_bot_faq-0.2.1.dist-info/WHEEL
django_bot_faq-0.2.1.dist-info/top_level.txt
django_bot_faq-0.2.1.dist-info/RECORD
