Metadata-Version: 2.1
Name: django-bot-faq
Version: 0.2.1
Summary: FAQ module
Home-page: https://github.com/IvanRomanchenko/django-bot-faq
Author: Ivan Romanchenko
Author-email: vanvanych789@gmail.com
License: UNKNOWN
Platform: UNKNOWN
Classifier: Programming Language :: Python :: 3.10
Classifier: Framework :: Django :: 4.0
Classifier: License :: OSI Approved :: MIT License
Classifier: Operating System :: OS Independent
Requires-Python: >=3.6
License-File: LICENSE
Requires-Dist: Django (==4.0.2)
Requires-Dist: django-mptt (==0.13.4)
Requires-Dist: django-cleanup (==6.0.0)
Requires-Dist: Pillow (==9.0.1)
Requires-Dist: pyTelegramBotAPI (==4.4.0)
Requires-Dist: psycopg2 (==2.9.3)
Requires-Dist: bot-storage (==1.0.1)
Requires-Dist: loguru (==0.6.0)
Requires-Dist: elasticsearch (==7.17.0)
Requires-Dist: elasticsearch-dsl (==7.4.0)
